gimmebio.covid-0.4.3-py3.6-nspkg.pth
gimmebio/covid/__init__.py
gimmebio/covid/api.py
gimmebio/covid/cli.py
gimmebio/covid/constants.py
gimmebio/covid/plots.py
gimmebio/covid/svs.py
gimmebio.covid-0.4.3.dist-info/METADATA
gimmebio.covid-0.4.3.dist-info/WHEEL
gimmebio.covid-0.4.3.dist-info/namespace_packages.txt
gimmebio.covid-0.4.3.dist-info/top_level.txt
gimmebio.covid-0.4.3.dist-info/RECORD
